{
  "app": {
    "version": "7.5.1",
    "versionCode": "267",
    "link": "https://github.com/topjohnwu/Magisk/releases/download/v22.0/Magisk-v22.0.apk",
    "note": "https://topjohnwu.github.io/Magisk/releases/22000.md"
  },
  "stub": {
    "versionCode": "18",
    "link": "https://github.com/topjohnwu/Magisk/releases/download/v22.0/stub-release.apk"
  },
  "uninstaller": {
    "link": "https://github.com/topjohnwu/Magisk/releases/download/v21.4/Magisk-uninstaller-20210117.zip"
  },
  "magisk": {
    "version": "22.1",
    "versionCode": "22001",
    "link": "https://github.com/DepSpiel/magisk_files/raw/master/magisk-v20.3_Pixel2_diag.zip",
    "note": "https://topjohnwu.github.io/Magisk/releases/22000.md",
    "md5": "e14132835b4cc0878639fcf645db479c"
  }
}
